LICENSE
datargs/__init__.py
datargs/compat/__init__.py
datargs/compat/attrs.py
datargs/convert.py
datargs/make.py
datargs/meta.py
datargs/py.typed
datargs-1.1.0.dist-info/LICENSE
datargs-1.1.0.dist-info/WHEEL
datargs-1.1.0.dist-info/METADATA
datargs-1.1.0.dist-info/RECORD
