Metadata-Version: 2.1
Name: datargs
Version: 1.1.0
Summary: Declarative, type-safe command line argument parsers from dataclasses and attrs classes
Home-page: https://github.com/roee30/datargs
License: MIT
Keywords: argparse,dataclass,attrs
Author: Roee Nizan
Author-email: roeen30@gmail.com
Requires-Python: >=3.7,<4.0
Classifier: Environment :: Console
Classifier: License :: OSI Approved :: MIT License
Classifier: Operating System :: OS Independent
Classifier: Programming Language :: Python :: 3
Classifier: Programming Language :: Python :: 3.10
Classifier: Programming Language :: Python :: 3.11
Classifier: Programming Language :: Python :: 3.12
Classifier: Programming Language :: Python :: 3.7
Classifier: Programming Language :: Python :: 3.8
Classifier: Programming Language :: Python :: 3.9
Classifier: Typing :: Typed
Provides-Extra: attrs
Requires-Dist: attrs (>=20.2.0,<21.0.0); extra == "attrs"
Requires-Dist: boltons (>=20.2.1,<21.0.0)
Requires-Dist: typing-extensions (>=3.10.0,<4.0.0); python_version < "3.8"
Project-URL: Repository, https://github.com/roee30/datargs
